geogif/__init__.py
geogif/gif.py
geogif-0.3.dist-info/LICENSE
geogif-0.3.dist-info/METADATA
geogif-0.3.dist-info/WHEEL
geogif-0.3.dist-info/RECORD
