Metadata-Version: 2.3
Name: geogif
Version: 0.3
Summary: Render xarray timestacks into GIFs
Home-page: https://geogif.readthedocs.io/en/latest/index.html
Author: Gabe Joseph
Author-email: gjoseph92@gmail.com
Requires-Python: >=3.8,<4.0
Classifier: Programming Language :: Python :: 3
Classifier: Programming Language :: Python :: 3.8
Classifier: Programming Language :: Python :: 3.9
Classifier: Programming Language :: Python :: 3.10
Classifier: Programming Language :: Python :: 3.11
Classifier: Programming Language :: Python :: 3.12
Classifier: Programming Language :: Python :: 3.13
Requires-Dist: Pillow (>=10.1,<11.0)
Requires-Dist: dask[delayed] (>=2021.4.1)
Requires-Dist: matplotlib (>=3.4.1,<4.0.0)
Requires-Dist: numpy (>=1.20.2,<2.0.0)
Requires-Dist: xarray (>=0.18)
Project-URL: Repository, https://github.com/gjoseph92/geogif
